RateMyProfessor_Database_APIs/__init__.py
RateMyProfessor_Database_APIs/helper_classes.py
RateMyProfessor_Database_APIs/helper_functions.py
RateMyProfessor_Database_APIs/helper_queries.py
RateMyProfessor_Database_APIs/main.py
RateMyProfessor_Database_APIs/test.py
RateMyProfessor_Database_APIs-1.1.1.dist-info/METADATA
RateMyProfessor_Database_APIs-1.1.1.dist-info/WHEEL
RateMyProfessor_Database_APIs-1.1.1.dist-info/top_level.txt
RateMyProfessor_Database_APIs-1.1.1.dist-info/RECORD
