Metadata-Version: 2.1
Name: RateMyProfessor-Database-APIs
Version: 1.1.1
Summary: RateMyProfessor.com database scrapper.
Author: Prakhar Bhartiya
Classifier: Programming Language :: Python :: 3
Classifier: Operating System :: OS Independent
